odoo9_addon_dbfilter_from_header-9.0.1.0.0.99.dev6-py2.7-nspkg.pth
odoo9_addon_dbfilter_from_header-9.0.1.0.0.99.dev6.dist-info/METADATA
odoo9_addon_dbfilter_from_header-9.0.1.0.0.99.dev6.dist-info/RECORD
odoo9_addon_dbfilter_from_header-9.0.1.0.0.99.dev6.dist-info/WHEEL
odoo9_addon_dbfilter_from_header-9.0.1.0.0.99.dev6.dist-info/namespace_packages.txt
odoo9_addon_dbfilter_from_header-9.0.1.0.0.99.dev6.dist-info/top_level.txt
odoo_addons/dbfilter_from_header/README.rst
odoo_addons/dbfilter_from_header/__init__.py
odoo_addons/dbfilter_from_header/__openerp__.py
odoo_addons/dbfilter_from_header/i18n/dbfilter_from_header.pot
odoo_addons/dbfilter_from_header/static/description/icon.png
